{
  "main": {
    "id": "541a133b2a28b7b0",
    "type": "split",
    "children": [
      {
        "id": "ff4f193da3d187fc",
        "type": "tabs",
        "children": [
          {
            "id": "52e1d04ce69ae92c",
            "type": "leaf",
            "state": {
              "type": "markdown",
              "state": {
                "file": "20260711_bevy-breakout-setup-troubleshooting.md",
                "mode": "source",
                "source": false
              },
              "icon": "lucide-file",
              "title": "20260711_bevy-breakout-setup-troubleshooting"
            }
          }
        ]
      }
    ],
    "direction": "vertical"
  },
  "left": {
    "id": "49fe6373dd5b9e4e",
    "type": "split",
    "children": [
      {
        "id": "737e30fbfa9810bd",
        "type": "tabs",
        "children": [
          {
            "id": "48c70b9fca180df1",
            "type": "leaf",
            "state": {
              "type": "file-explorer",
              "state": {
                "sortOrder": "alphabetical",
                "autoReveal": false
              },
              "icon": "lucide-folder-closed",
              "title": "ファイルエクスプローラ"
            }
          },
          {
            "id": "49050e5bc832b12d",
            "type": "leaf",
            "state": {
              "type": "search",
              "state": {
                "query": "",
                "matchingCase": false,
                "explainSearch": false,
                "collapseAll": false,
                "extraContext": false,
                "sortOrder": "alphabetical"
              },
              "icon": "lucide-search",
              "title": "検索"
            }
          },
          {
            "id": "b3e1ccc384953a55",
            "type": "leaf",
            "state": {
              "type": "bookmarks",
              "state": {},
              "icon": "lucide-bookmark",
              "title": "ブックマーク"
            }
          }
        ]
      }
    ],
    "direction": "horizontal",
    "width": 300
  },
  "right": {
    "id": "666c502e87c199b1",
    "type": "split",
    "children": [
      {
        "id": "6f84d8ca54b18747",
        "type": "tabs",
        "children": [
          {
            "id": "93f287f735dc79ca",
            "type": "leaf",
            "state": {
              "type": "backlink",
              "state": {
                "file": "20260711_bevy-breakout-setup-troubleshooting.md",
                "collapseAll": false,
                "extraContext": false,
                "sortOrder": "alphabetical",
                "showSearch": false,
                "searchQuery": "",
                "backlinkCollapsed": false,
                "unlinkedCollapsed": true
              },
              "icon": "links-coming-in",
              "title": "20260711_bevy-breakout-setup-troubleshootingへのバックリンク"
            }
          },
          {
            "id": "deb9703e7aa3004b",
            "type": "leaf",
            "state": {
              "type": "outgoing-link",
              "state": {
                "file": "20260711_bevy-breakout-setup-troubleshooting.md",
                "linksCollapsed": false,
                "unlinkedCollapsed": true
              },
              "icon": "links-going-out",
              "title": "20260711_bevy-breakout-setup-troubleshootingからのアウトゴーイングリンク"
            }
          },
          {
            "id": "d38e71fa24c32675",
            "type": "leaf",
            "state": {
              "type": "tag",
              "state": {
                "sortOrder": "frequency",
                "useHierarchy": true,
                "showSearch": false,
                "searchQuery": ""
              },
              "icon": "lucide-tags",
              "title": "タグ"
            }
          },
          {
            "id": "6a3bc0628e075e30",
            "type": "leaf",
            "state": {
              "type": "all-properties",
              "state": {
                "sortOrder": "frequency",
                "showSearch": false,
                "searchQuery": ""
              },
              "icon": "lucide-archive",
              "title": "すべてのプロパティ"
            }
          },
          {
            "id": "33f16fec78f3665e",
            "type": "leaf",
            "state": {
              "type": "outline",
              "state": {
                "file": "20260711_bevy-breakout-setup-troubleshooting.md",
                "followCursor": false,
                "showSearch": false,
                "searchQuery": ""
              },
              "icon": "lucide-list",
              "title": "20260711_bevy-breakout-setup-troubleshootingのアウトライン"
            }
          }
        ]
      }
    ],
    "direction": "horizontal",
    "width": 300,
    "collapsed": true
  },
  "left-ribbon": {
    "hiddenItems": {
      "switcher:クイックスイッチャーを開く": false,
      "graph:グラフビューを開く": false,
      "canvas:新規キャンバスを作成": false,
      "daily-notes:今日のデイリーノートを開く": false,
      "templates:テンプレートを挿入": false,
      "command-palette:コマンドパレットを開く": false,
      "bases:新規ベースを作成": false
    }
  },
  "active": "52e1d04ce69ae92c",
  "lastOpenFiles": [
    "20260717_bevy-add-systems-schedule-labels.md",
    "20260717_wasm-dispatch-event-mechanism.md",
    "20260717_game-state-and-clear-notification-impl.md",
    "20260717_bevy-to-frontend-event-notification.md",
    "20260716_bevy-resource-res-resmut-basics.md",
    "20260716_background-rendering-and-bevy-system-params.md",
    "20260715_main-rs-module-split.md",
    "20260715_aspect-ratio-and-letterbox.md",
    "20260715_brick-image-rendering.md",
    "20260711_why-wasm-is-secure.md",
    "20260711_wasm-build-size-optimization.md",
    "20260711_react-to-bevy-init-params.md",
    "20260711_wasm-bevy-browser-verification.md",
    "20260711_react-to-bevy-background-injection.md",
    "20260711_external-image-cors-and-formats.md",
    "20260711_bevy-wasm-react-integration.md"
  ]
}